README.rst
setup.py
lsptrain/__init__.py
lsptrain.egg-info/PKG-INFO
lsptrain.egg-info/SOURCES.txt
lsptrain.egg-info/dependency_links.txt
lsptrain.egg-info/requires.txt
lsptrain.egg-info/top_level.txt
lsptrain/nlp_classification/__init__.py
lsptrain/nlp_classification/model.py
lsptrain/nlp_classification/train_scripts.py
lsptrain/nlp_classification_predictor/__init__.py
lsptrain/nlp_classification_predictor/predictor.py
lsptrain/nlp_info_extract/__init__.py
lsptrain/nlp_info_extract/download_pretrained_model.py
lsptrain/nlp_info_extract/ernie.py
lsptrain/nlp_info_extract/evaluate.py
lsptrain/nlp_info_extract/model.py
lsptrain/nlp_info_extract/train_scripts.py
lsptrain/nlp_info_extract/util.py
lsptrain/nlp_similarity_predictor/__init__.py
lsptrain/nlp_similarity_predictor/predictor.py