Metadata-Version: 2.1
Name: lsptrain
Version: 0.0.62
Summary: nlp for anyone
Home-page: https://www.gitee.com/ykallan/lsptrain
Author: ykallan
Author-email: 815583442@qq.com
License: BSD License
Platform: all
Requires-Python: >=3.7
